grype_mcp/__init__.py
grype_mcp/server.py
grype_mcp-0.4.0.dist-info/METADATA
grype_mcp-0.4.0.dist-info/WHEEL
grype_mcp-0.4.0.dist-info/entry_points.txt
grype_mcp-0.4.0.dist-info/licenses/LICENSE
grype_mcp-0.4.0.dist-info/RECORD
