Metadata-Version: 2.4
Name: grype-mcp
Version: 0.4.0
Summary: Official Anchore Grype MCP Server for AI-assisted vulnerability scanning
Project-URL: Homepage, https://github.com/anchore/grype-mcp
Project-URL: Documentation, https://github.com/anchore/grype-mcp#readme
Project-URL: Repository, https://github.com/anchore/grype-mcp.git
Project-URL: Issues, https://github.com/anchore/grype-mcp/issues
Project-URL: Changelog, https://github.com/anchore/grype-mcp/releases
Author-email: Alan Pope <alan.pope@anchore.com>
Maintainer-email: Alan Pope <alan.pope@anchore.com>
License: Apache-2.0
License-File: LICENSE
Keywords: ai,anchore,grype,mcp,scanning,security,vulnerability
Classifier: Development Status :: 4 - Beta
Classifier: Intended Audience :: Developers
Classifier: License :: OSI Approved :: Apache Software License
Classifier: Operating System :: OS Independent
Classifier: Programming Language :: Python :: 3
Classifier: Programming Language :: Python :: 3.10
Classifier: Programming Language :: Python :: 3.11
Classifier: Programming Language :: Python :: 3.12
Classifier: Topic :: Security
Classifier: Topic :: Software Development
Classifier: Topic :: System :: Systems Administration
Requires-Python: >=3.10
Requires-Dist: click>=8.0.0
Requires-Dist: mcp>=1.0.0
Provides-Extra: dev
Requires-Dist: black>=23.0.0; extra == 'dev'
Requires-Dist: build>=0.10.0; extra == 'dev'
Requires-Dist: pytest-asyncio>=0.21.0; extra == 'dev'
Requires-Dist: pytest>=7.0.0; extra == 'dev'
Requires-Dist: ruff>=0.1.0; extra == 'dev'
Requires-Dist: twine>=4.0.0; extra == 'dev'
